odoo/addons/l10n_it_delivery_note_inter_warehouse/README.rst
odoo/addons/l10n_it_delivery_note_inter_warehouse/__init__.py
odoo/addons/l10n_it_delivery_note_inter_warehouse/__manifest__.py
odoo/addons/l10n_it_delivery_note_inter_warehouse/i18n/it.po
odoo/addons/l10n_it_delivery_note_inter_warehouse/i18n/l10n_it_delivery_note_inter_warehouse.pot
odoo/addons/l10n_it_delivery_note_inter_warehouse/models/__init__.py
odoo/addons/l10n_it_delivery_note_inter_warehouse/models/stock_delivery_note.py
odoo/addons/l10n_it_delivery_note_inter_warehouse/readme/CONTRIBUTORS.rst
odoo/addons/l10n_it_delivery_note_inter_warehouse/readme/DESCRIPTION.rst
odoo/addons/l10n_it_delivery_note_inter_warehouse/static/description/icon.png
odoo/addons/l10n_it_delivery_note_inter_warehouse/static/description/index.html
odoo/addons/l10n_it_delivery_note_inter_warehouse/tests/__init__.py
odoo/addons/l10n_it_delivery_note_inter_warehouse/tests/test_delivery_note_inter_warehouse.py
odoo/addons/l10n_it_delivery_note_inter_warehouse/views/stock_picking_views.xml
odoo/addons/l10n_it_delivery_note_inter_warehouse/wizards/__init__.py
odoo/addons/l10n_it_delivery_note_inter_warehouse/wizards/delivery_note_select.py
odoo/addons/l10n_it_delivery_note_inter_warehouse/wizards/delivery_note_select.xml
odoo14_addon_l10n_it_delivery_note_inter_warehouse-14.0.1.0.1.dist-info/METADATA
odoo14_addon_l10n_it_delivery_note_inter_warehouse-14.0.1.0.1.dist-info/WHEEL
odoo14_addon_l10n_it_delivery_note_inter_warehouse-14.0.1.0.1.dist-info/top_level.txt
odoo14_addon_l10n_it_delivery_note_inter_warehouse-14.0.1.0.1.dist-info/RECORD
